yougile/__init__.py
yougile/request.py
yougile/models/__init__.py
yougile/models/auth.py
yougile/models/boards.py
yougile/models/chatmessages.py
yougile/models/columns.py
yougile/models/companies.py
yougile/models/departments.py
yougile/models/employees.py
yougile/models/files.py
yougile/models/groupchats.py
yougile/models/projectroles.py
yougile/models/projects.py
yougile/models/sprintsticker.py
yougile/models/sprintstickerstate.py
yougile/models/stringsticker.py
yougile/models/stringstickerstate.py
yougile/models/tasks.py
yougile/models/webhooks.py
yougile_api-1.1.0.dist-info/licenses/LICENSE
yougile_api-1.1.0.dist-info/METADATA
yougile_api-1.1.0.dist-info/WHEEL
yougile_api-1.1.0.dist-info/top_level.txt
yougile_api-1.1.0.dist-info/RECORD
