Metadata-Version: 2.4
Name: yougile-api
Version: 1.1.0
Summary: Yougile API models
Author-email: txello <txello7@proton.me>
Project-URL: Homepage, https://github.com/txello/YouGile
Project-URL: Issues, https://github.com/txello/YouGile/issues
Classifier: Programming Language :: Python :: 3
Classifier: License :: OSI Approved :: MIT License
Classifier: Operating System :: OS Independent
Requires-Python: >=3.8
License-File: LICENSE
Requires-Dist: pydantic
Requires-Dist: requests
Dynamic: license-file
